filter_dict.py
FilterDict-0.2.1576267427.dist-info/LICENSE.txt
FilterDict-0.2.1576267427.dist-info/METADATA
FilterDict-0.2.1576267427.dist-info/WHEEL
FilterDict-0.2.1576267427.dist-info/entry_points.txt
FilterDict-0.2.1576267427.dist-info/top_level.txt
FilterDict-0.2.1576267427.dist-info/RECORD
