Metadata-Version: 2.1
Name: FilterDict
Version: 0.2.1576267427
Summary: Store data in JSON format
Home-page: https://github.com/JulianKimmig/filter_dict
Author: Julian Kimmig
Author-email: julian-kimmig@gmx.net
License: UNKNOWN
Platform: UNKNOWN
Classifier: Programming Language :: Python :: 3
Classifier: License :: OSI Approved :: MIT License
Classifier: Operating System :: OS Independent
